D47crunch/__init__.py
d47crunch-2.5.3.dist-info/entry_points.txt
d47crunch-2.5.3.dist-info/licenses/LICENSE
d47crunch-2.5.3.dist-info/WHEEL
d47crunch-2.5.3.dist-info/METADATA
d47crunch-2.5.3.dist-info/RECORD
