Metadata-Version: 2.4
Name: D47crunch
Version: 2.5.3
Summary: Standardization and analytical error propagation of Δ47 and Δ48 clumped-isotope measurements
Author-email: Mathieu Daëron <mathieu@daeron.fr>
Requires-Python: >= 3.12
Classifier: License :: OSI Approved :: MIT License
License-File: LICENSE
Requires-Dist: numpy >=1.21
Requires-Dist: scipy >=1.7.0
Requires-Dist: matplotlib >=3.4.2
Requires-Dist: lmfit >=1.0.2
Requires-Dist: typer >=0.17
Requires-Dist: rich
Project-URL: Documentation, https://mdaeron.github.io/D47crunch
Project-URL: Home, https://github.com/mdaeron/D47crunch
